{
  "_fv": 39,
  "_type": "tool",
  "definition": {
    "renderType": 0,
    "texture": "netherite_shovel",
    "customModelName": "Normal",
    "name": "Netherite Shovel",
    "specialInfo": [],
    "creativeTab": {
      "value": "TOOLS"
    },
    "toolType": "Spade",
    "harvestLevel": 4,
    "efficiency": 9.0,
    "attackSpeed": 1.0,
    "enchantability": 15,
    "damageVsEntity": 6.5,
    "usageCount": 2031,
    "blocksAffected": [],
    "hasGlow": false,
    "repairItems": [
      {
        "value": "Items.NETHERITE_INGOT"
      },
      {
        "value": "Items.NETHERITE_SCRAP"
      }
    ],
    "immuneToFire": true,
    "stayInGridWhenCrafting": false,
    "damageOnCrafting": false
  }
}